agton/dedust/__init__.py
agton/dedust/events.py
agton/dedust/contracts/__init__.py
agton/dedust/contracts/factory.py
agton/dedust/contracts/jetton_vault.py
agton/dedust/contracts/native_vault.py
agton/dedust/contracts/pool.py
agton/dedust/messages/__init__.py
agton/dedust/messages/deposit_liquidity.py
agton/dedust/messages/swap.py
agton/dedust/payloads/__init__.py
agton/dedust/payloads/deposit_liquidity.py
agton/dedust/payloads/swap.py
agton/dedust/types/__init__.py
agton/dedust/types/asset.py
agton/dedust/types/pool_params.py
agton/dedust/types/pool_type.py
agton/dedust/types/swap_kind.py
agton/dedust/types/swap_params.py
agton/dedust/types/swap_step.py
agton_dedust-0.2.4.dist-info/licenses/LICENSE
agton_dedust-0.2.4.dist-info/METADATA
agton_dedust-0.2.4.dist-info/WHEEL
agton_dedust-0.2.4.dist-info/top_level.txt
agton_dedust-0.2.4.dist-info/RECORD
