Metadata-Version: 2.4
Name: agton-dedust
Version: 0.2.4
Summary: TON Blockchain DeDust SDK
Author-email: Alexey Gosunov <agosunov@gmail.com>
License: MIT
Project-URL: Homepage, https://github.com/gosunov/agton
Requires-Python: >=3.12
License-File: LICENSE
Requires-Dist: agton>=0.2.4
Dynamic: license-file
